getnews/Logging_skelton.py
getnews/__init__.py
getnews/main.py
getnews-0.0.2.dist-info/Licence.txt
getnews-0.0.2.dist-info/METADATA
getnews-0.0.2.dist-info/WHEEL
getnews-0.0.2.dist-info/top_level.txt
getnews-0.0.2.dist-info/RECORD
